pytorch_custom_utils/__init__.py
pytorch_custom_utils/accelerate_utils.py
pytorch_custom_utils/get_adam_optimizer.py
pytorch_custom_utils/module_device.py
pytorch_custom_utils/optimizer_scheduler_warmup.py
pytorch_custom_utils/save_load.py
pytorch_custom_utils/total_parameters.py
pytorch_custom_utils/utils.py
pytorch_custom_utils-0.0.21.dist-info/LICENSE
pytorch_custom_utils-0.0.21.dist-info/METADATA
pytorch_custom_utils-0.0.21.dist-info/WHEEL
pytorch_custom_utils-0.0.21.dist-info/top_level.txt
pytorch_custom_utils-0.0.21.dist-info/RECORD
