Metadata-Version: 2.1
Name: pytorch-custom-utils
Version: 0.0.21
Summary: Pytorch Custom Utils
Home-page: https://github.com/lucidrains/pytorch-custom-utils
Author: Phil Wang
Author-email: lucidrains@gmail.com
License: MIT
Keywords: pytorch,accelerate
Classifier: Development Status :: 4 - Beta
Classifier: Intended Audience :: Developers
Classifier: Topic :: Scientific/Engineering :: Artificial Intelligence
Classifier: License :: OSI Approved :: MIT License
Classifier: Programming Language :: Python :: 3.6
License-File: LICENSE
Requires-Dist: accelerate
Requires-Dist: optree
Requires-Dist: pytorch-warmup
Requires-Dist: torch >=2.0
